sbgnrender/RendererClient.py
sbgnrender/__init__.py
sbgnrender/index.html
sbgnrender/app/__init__.py
sbgnrender/app/bundle.js
sbgnrender/app/main.js
sbgnrender/app/css/chise.css
sbgnrender/app/img/Thumbs.db
sbgnrender/app/img/add-edge-cursor.svg
sbgnrender/app/img/add-node-cursor.svg
sbgnrender/app/img/add.svg
sbgnrender/app/img/af-legend.svg
sbgnrender/app/img/cancel.svg
sbgnrender/app/img/fix-error.svg
sbgnrender/app/img/i-vis.png
sbgnrender/app/img/interaction_legend_sbgn.png
sbgnrender/app/img/loading-small.gif
sbgnrender/app/img/loading.gif
sbgnrender/app/img/lock.svg
sbgnrender/app/img/newt-icon.png
sbgnrender/app/img/newt-logo.png
sbgnrender/app/img/node_legend_sbgn.png
sbgnrender/app/img/open-lock.svg
sbgnrender/app/img/pd-legend.svg
sbgnrender/app/img/select-cursor.svg
sbgnrender/app/img/sif-legend.svg
sbgnrender/app/img/target-cursor.svg
sbgnrender/app/img/zoom-cursor.svg
sbgnrender/app/img/align/align-horizontal-bottom.svg
sbgnrender/app/img/align/align-horizontal-middle.svg
sbgnrender/app/img/align/align-horizontal-top.svg
sbgnrender/app/img/align/align-vertical-center.svg
sbgnrender/app/img/align/align-vertical-left.svg
sbgnrender/app/img/align/align-vertical-right.svg
sbgnrender/app/img/align/align.svg
sbgnrender/app/img/edges/activates.svg
sbgnrender/app/img/edges/catalysis-precedes.svg
sbgnrender/app/img/edges/catalysis.svg
sbgnrender/app/img/edges/chemical-affects.svg
sbgnrender/app/img/edges/consumption-controled-by.svg
sbgnrender/app/img/edges/consumption.svg
sbgnrender/app/img/edges/controls-expression-of.svg
sbgnrender/app/img/edges/controls-phosphorylation-of.svg
sbgnrender/app/img/edges/controls-production-of.svg
sbgnrender/app/img/edges/controls-state-change-of.svg
sbgnrender/app/img/edges/controls-transport-of-chemical.svg
sbgnrender/app/img/edges/controls-transport-of.svg
sbgnrender/app/img/edges/dephosphorylates.svg
sbgnrender/app/img/edges/downregulates-expression.svg
sbgnrender/app/img/edges/in-complex-with.svg
sbgnrender-1.0.0a9.dist-info/LICENSE.md
sbgnrender-1.0.0a9.dist-info/METADATA
sbgnrender-1.0.0a9.dist-info/WHEEL
sbgnrender-1.0.0a9.dist-info/top_level.txt
sbgnrender-1.0.0a9.dist-info/RECORD
