Metadata-Version: 2.1
Name: sbgnrender
Version: 1.0.0a9
Summary: A SBGN rendering library
Home-page: https://github.com/vincent-noel/SBGNRenderAPI
Author: Vincent Noël
Author-email: contact@vincent-noel.fr
License: UNKNOWN
Platform: UNKNOWN
Requires-Dist: selenium
